fastapi_directory_routing/__init__.py
fastapi_directory_routing/__version__.py
fastapi_directory_routing/core/__init__.py
fastapi_directory_routing/core/directory_router.py
tests/__init__.py
fastapi_directory_routing-0.0.1.dist-info/METADATA
fastapi_directory_routing-0.0.1.dist-info/WHEEL
fastapi_directory_routing-0.0.1.dist-info/top_level.txt
fastapi_directory_routing-0.0.1.dist-info/RECORD
