Metadata-Version: 2.1
Name: fastapi-directory-routing
Version: 0.0.1
Summary: The file system-based FastAPI router automatically generates the routing structure from the file system.
Author: Ebubekir Karanfil
Author-email: karanfilebubekir@gmail.com
License: MIT
